pixelart2tgs/__main__.py
pixelart2tgs/chain_generator.py
pixelart2tgs/contour_generator.py
pixelart2tgs/converter_types.py
pixelart2tgs/lottie_generator.py
pixelart2tgs/shape_generator.py
pixelart2tgs/templates.py
pixelart2tgs-1.0.1.dist-info/LICENSE.txt
pixelart2tgs-1.0.1.dist-info/METADATA
pixelart2tgs-1.0.1.dist-info/WHEEL
pixelart2tgs-1.0.1.dist-info/top_level.txt
pixelart2tgs-1.0.1.dist-info/RECORD
