Metadata-Version: 2.1
Name: pixelart2tgs
Version: 1.0.1
Summary: Simple .gif to .tgs converter cli utility
Author-email: sliva0 <sliva0mk@gmail.com>
License: MIT License
Project-URL: Homepage, https://github.com/sliva0/pixelart2tgs
Project-URL: Author's telegram, https://t.me/sliva0
Classifier: Programming Language :: Python :: 3
Classifier: License :: OSI Approved :: MIT License
Classifier: Operating System :: OS Independent
Requires-Python: >=3.8
License-File: LICENSE.txt
